README.rst
setup.py
anchorman/__init__.py
anchorman/candidate.py
anchorman/elements.py
anchorman/intervals.py
anchorman/main.py
anchorman/result.py
anchorman/settings.py
anchorman/units.py
anchorman/utils.py
anchorman.egg-info/PKG-INFO
anchorman.egg-info/SOURCES.txt
anchorman.egg-info/dependency_links.txt
anchorman.egg-info/requires.txt
anchorman.egg-info/top_level.txt