Metadata-Version: 1.1
Name: anchorman
Version: 0.5.3
Summary: Anchorman takes a list of terms and a text. It finds the terms in this text and replaces them with another representation.
Home-page: https://github.com/rebeling/anchorman
Author: matthias rebel
Author-email: webmaster@rebeling.net
License: Apache 2.0
Keywords: intext-links,linking,annotations,tags,hypertext,markup
Platform: UNKNOWN
Classifier: Development Status :: 3 - Alpha
Classifier: Intended Audience :: Developers
Classifier: Natural Language :: English
Classifier: Programming Language :: Python
Classifier: Programming Language :: Python :: 2.7
Classifier: Programming Language :: Python :: 3.5
Classifier: Topic :: Text Processing :: Markup
